<root>
<tweet>
	<text>Golden Globes, lots of fashion messes...but glad Argo won. Really good movie, along w Moonrise Kingdom and Salmon Fishing Yeman.</text>
	<name>Dpharmakis23</name>
</tweet>
<tweet>
	<text>RT @RPLife: 2 Red Carpet HQs added and maybe my favorites of the night http://t.co/Fiq08m7i</text>
	<name>dri_violet</name>
</tweet>
<tweet>
	<text>After watching the Golden Globes it made me want to watch Les Mis again. It's gonna be a late night tonight.</text>
	<name>JessBess4</name>
</tweet>
<tweet>
	<text>I'm pretty how I've felt during the Golden Globes is how most of my followers feel during a NASCAR race/football game. #TweetOverload</text>
	<name>JordanTMcGraw</name>
</tweet>
<tweet>
	<text>RT @LaAbuela961: Hay personas que solo compran ropa en Jacarandas pero se pasaron criticando los vestuarios de los famosos en los Golden Globes. #NoMeJodan</text>
	<name>silvita_hdez</name>
</tweet>
<tweet>
	<text>No puedo creer que ya hayan gifs de los Golden Globes, permiso me voy a Tumblr.</text>
	<name>JennyPadawan</name>
</tweet>
<tweet>
	<text>My fave dresses at Golden Globes 👗 #fashion #amyadams #meganfox #rosiehw #cantsleep http://t.co/ZFMALMkA</text>
	<name>Gill27031</name>
</tweet>
<tweet>
	<text>"Kristen Stewart Makes Surprise Appearance At 2013 Golden Globes" OI???????????</text>
	<name>maricheq</name>
</tweet>
<tweet>
	<text>Jessica Chastain, Best Actress Drama Winner At Golden Globes 2013 http://t.co/MmUc3iPJ</text>
	<name>NehaThakur27</name>
</tweet>
<tweet>
	<text>😱👏 Golden Globes 2013 http://t.co/2y6kNxwn vía @glamourmaguk</text>
	<name>isafloresp</name>
</tweet>
<tweet>
	<text>Jennifer Lawrence vs. Zooey Deschanel: It's the Golden Globes Red Carpet Pose-Off!: It's a lady in red showdown! Jennifer Lawrence an...</text>
	<name>taylor_debery</name>
</tweet>
<tweet>
	<text>'Argo,' 'Les Miz' win best-picture Golden Globes; Day-Lewis, Chastain take drama acting awards: http://t.co/ZVwVwWlb #GoldenGlobes</text>
	<name>rootbear67</name>
</tweet>
<tweet>
	<text>Tina Fey Jabs Taylor Swift At Golden Globes http://t.co/pkvrUDny</text>
	<name>pizzaessa_blog</name>
</tweet>
<tweet>
	<text>Golden Globes 2013 Worst-Dressed List: See The Fashion Flops Of The Night! (PHOTOS) http://t.co/22QnBSuC</text>
	<name>NehaThakur27</name>
</tweet>
<tweet>
	<text>@GDeLaurentiis pretty lady heading to the Golden Globes! Thank you @herveleger and @davidyurman! Make up @foxyfleet http://t.co/Jpl5B95Y</text>
	<name>SamStyles</name>
</tweet>
<tweet>
	<text>Jodie Foster: 'I'm Not Honey Boo Boo Child': Jodie Foster’s speech at the Golden Globes will definitely be the talk... http://t.co/KjOQVOMF</text>
	<name>neutralnews</name>
</tweet>
<tweet>
	<text>'Girls' Night: HBO Series Nabs Two Golden Globes http://t.co/nDC4NW8s</text>
	<name>jimmylandaburu</name>
</tweet>
<tweet>
	<text>Golden Globes 2013: What the Stars Wore! http://t.co/aDACbB4w</text>
	<name>CelebrityPoints</name>
</tweet>
<tweet>
	<text>Love how Meryl Streep doesn't go to the Golden Globes cos she isn't feeling well. Bad Arse Ma Focker. #QueenOfHollywood</text>
	<name>faithkelly</name>
</tweet>
<tweet>
	<text>It will be an award in &amp; of itself if I catch good Zzzs tonight! Golden Globes left me feeling all sorts of "uncomfortables."</text>
	<name>AmourColette</name>
</tweet>
<tweet>
	<text>Latest: 'Girls' Night: HBO Series Nabs Two Golden Globes http://t.co/XXLG0JRt #MusicNews</text>
	<name>putupthesound</name>
</tweet>
<tweet>
	<text>Golden Globes 2013: What the Stars Wore! http://t.co/tpCZsdzX</text>
	<name>GoCelebrityUS</name>
</tweet>
<tweet>
	<text>NYTimes: 'Argo,' 'Les Miz,' Homeland' and 'Girls' Win Big at the Golden Globes http://t.co/MdOoo3gs</text>
	<name>Geancarlla</name>
</tweet>
<tweet>
	<text>Did they have mug shots at the golden globes?! DID THEY?! #localnews http://t.co/KA8Nsh2h</text>
	<name>reynaramirez22</name>
</tweet>
<tweet>
	<text>RT @theblcklst: Black List scripts have now won 4 of the last 5 Golden Globes for Best Drama.</text>
	<name>andrecole</name>
</tweet>
<tweet>
	<text>Jodie Foster Officially Comes Out as Gay in Moving Golden Globes Speech http://t.co/g9mBfj4j</text>
	<name>CelebrityPoints</name>
</tweet>
<tweet>
	<text>#UCWRadio  'Argo,' 'Les Mis' win at Golden Globes http://t.co/zS0UNknl #movies</text>
	<name>UCWNews</name>
</tweet>
<tweet>
	<text>'Les Miserables' Best Picture, Musical Or Comedy Winner At 2013 Golden Globes http://t.co/Bp0EjJ6y</text>
	<name>NehaThakur27</name>
</tweet>
<tweet>
	<text>RT @eonline: Best Actor, TV Series Comedy: Don Cheadle for House of Lies! #GoldenGlobes http://t.co/mTzTn5TI (The night's first big surprise!)</text>
	<name>DaeMichelle9</name>
</tweet>
<tweet>
	<text>Jodie Foster Officially Comes Out as Gay in Moving Golden Globes Speech http://t.co/BxJShWiS</text>
	<name>GoCelebrityUS</name>
</tweet>
<tweet>
	<text>RT @PerezHilton: @NBC Tina Fey &amp; Amy Poehler Are The Whole Package At The Globes http://t.co/H8g1VNdy</text>
	<name>bobbiekingsbury</name>
</tweet>
<tweet>
	<text>Lea Michele Shows Off Super-Tan Body at 2013 Golden Globes http://t.co/zkYT70mD</text>
	<name>CelebrityPoints</name>
</tweet>
<tweet>
	<text>@justusdonuts and then evan was at the golden globes. and then, michael phelps destroyed a sandwich at subway.</text>
	<name>flailingsequins</name>
</tweet>
<tweet>
	<text>Golden Globes 2013: What the Stars Wore! http://t.co/rXSuH5Qb</text>
	<name>JenifferLovers</name>
</tweet>
<tweet>
	<text>RT @nerdywonka: Ben Affleck won Best Director for Argo @ Critics Choice Movie Awards AND the Golden Globes. Translation: “Screw You Oscars.”</text>
	<name>Halibutron</name>
</tweet>
<tweet>
	<text>Happy Monday!
My picks for hair and makeup that I loved at the #goldenglobes :)
#beauty #hair #makeup #skincare
http://t.co/wQMk5kCk</text>
	<name>staceycamacho</name>
</tweet>
<tweet>
	<text>Lea Michele Shows Off Super-Tan Body at 2013 Golden Globes http://t.co/dReEbx87</text>
	<name>GoCelebrityUS</name>
</tweet>
<tweet>
	<text>Jodie Foster Speech: Retirement Speculation At Golden Globes (VIDEO) http://t.co/cHK1pvCS</text>
	<name>DilipSinha3</name>
</tweet>
<tweet>
	<text>Jodie Foster Speech: Retirement Speculation At Golden Globes (VIDEO) http://t.co/reJkL7kq</text>
	<name>HimadriGupta</name>
</tweet>
<tweet>
	<text>Jodie Foster Speech: Retirement Speculation At Golden Globes (VIDEO) http://t.co/CkzpnnKv</text>
	<name>LimpaGhosh</name>
</tweet>
<tweet>
	<text>Jodie Foster Officially Comes Out as Gay in Moving Golden Globes Speech http://t.co/R6MPKKMM</text>
	<name>JenifferLovers</name>
</tweet>
<tweet>
	<text>Listen to Winners From the Golden Globes: Adele and ‘Life of Pi’ http://t.co/uODjORlc</text>
	<name>chiello167</name>
</tweet>
<tweet>
	<text>RT @benedictphoto: Golden globes 2013 http://t.co/fu75x4rJ</text>
	<name>akitu_s</name>
</tweet>
<tweet>
	<text>Best Actor, Drama: Golden Globe For Film Goes To Daniel Day-Lewis http://t.co/fFn1ETQe</text>
	<name>DilipSinha3</name>
</tweet>
<tweet>
	<text>RT @YahooOmg: Thanks for watching the #GoldenGlobes with us! Now head here http://t.co/vWJ2EdFl for our @omgInsider live post-show!</text>
	<name>YahooMovies</name>
</tweet>
<tweet>
	<text>Best Actor, Drama: Golden Globe For Film Goes To Daniel Day-Lewis http://t.co/uXGYSsN8</text>
	<name>HimadriGupta</name>
</tweet>
<tweet>
	<text>Twitter, Hollywood Flip for Bill Clinton at Golden Globes - Bill Clinton continued his "Remember How Awesome I Am" t... http://t.co/SKyriysN</text>
	<name>chiello167</name>
</tweet>
<tweet>
	<text>Best Actor, Drama: Golden Globe For Film Goes To Daniel Day-Lewis http://t.co/CNlxQZMO</text>
	<name>LimpaGhosh</name>
</tweet>
<tweet>
	<text>Hope everyone is liking my version of the golden globes ! LOL</text>
	<name>ItsPaulyC</name>
</tweet>
<tweet>
	<text>Lea Michele Shows Off Super-Tan Body at 2013 Golden Globes http://t.co/sLssnaQB</text>
	<name>JenifferLovers</name>
</tweet>
<tweet>
	<text>Listen to Winners From the Golden Globes: Adele and ‘Life of Pi’ http://t.co/4EACPvAP</text>
	<name>kenceanderson</name>
</tweet>
<tweet>
	<text>RT @TGrunin: Who needs to watch the golden globes when @Greg_Good23 is doing second by second twitter updates?</text>
	<name>DietDunkinDew</name>
</tweet>
<tweet>
	<text>Jennifer Lopez @ 2013 Golden Globes Photos - Makeup, Dress, Hair: Jennifer Lopez @ 2013 Golden Globes 70th Annual Golden Globes: Jenn...</text>
	<name>NormandDrouin</name>
</tweet>
<tweet>
	<text>Golden Globes 2013: What the Stars Wore! http://t.co/jmyubVSn</text>
	<name>CelebrityOprah</name>
</tweet>
<tweet>
	<text>http://t.co/XYil11rS Jodie Foster's Stirring Golden Globes Speech: 'I Already Did My Coming Out a Thousand Years Ago'</text>
	<name>VintageVHS</name>
</tweet>
<tweet>
	<text>Kristen Bell @ 2013 Golden Globes Photos - Makeup, Dress, Hair: Kristen Bell @ 2013 Golden Globes 70th Annual Golden Globes: Kristen ...</text>
	<name>NormandDrouin</name>
</tweet>
<tweet>
	<text>Jodie Foster Officially Comes Out as Gay in Moving Golden Globes Speech http://t.co/d5yjogu9</text>
	<name>CelebrityOprah</name>
</tweet>
<tweet>
	<text>RT @youlookthesame: Everyone should see Robert Downey Jr in 'Home for the Holidays' directed by Jodi Foster. One of my favs. #Golden #Globes</text>
	<name>redhead_9au</name>
</tweet>
<tweet>
	<text>2013 Golden Globes Makeup, Hair, Dresses Recap: Claire Danes @ 2013 Golden Globes 2013 Golden Globes Makeup, Hair, Dresses Recap You ...</text>
	<name>NormandDrouin</name>
</tweet>
<tweet>
	<text>Jodie Foster Speech: Retirement Speculation At Golden Globes (VIDEO) http://t.co/6OGOIDTd</text>
	<name>BhaskarBanerje4</name>
</tweet>
<tweet>
	<text>RT @mediaite: Jodie Foster Comes Out… As Pro-Privacy… In Epic, Cryptic, Moving Acceptance Speech At Golden Globes (VIDEO) http://t.co/C5ybir3Z</text>
	<name>ketagoesglobal</name>
</tweet>
<tweet>
	<text>Lea Michele Shows Off Super-Tan Body at 2013 Golden Globes http://t.co/jFX9VPxZ</text>
	<name>CelebrityOprah</name>
</tweet>
<tweet>
	<text>'Girls' Night: HBO Series Nabs Two Golden Globes - Don Cheadle rounds out TV comedy category with ‘House of... http://t.co/QLcai1xJ</text>
	<name>anoems</name>
</tweet>
<tweet>
	<text>The Golden Globes® have come and gone and we’re proud to announce Django Unchained took home two awards (Best... http://t.co/6PIwSsqZ</text>
	<name>inmgn</name>
</tweet>
<tweet>
	<text>Jessica Chastain, Best Actress Drama Winner At Golden Globes 2013 http://t.co/nWlzHUia</text>
	<name>HimadriGupta</name>
</tweet>
<tweet>
	<text>Listen to Winners From the Golden Globes: Adele and ‘Life of Pi’ http://t.co/0LEyHN2z</text>
	<name>hootchristian</name>
</tweet>
<tweet>
	<text>Twitter, Hollywood Flip for Bill Clinton at Golden Globes - Bill Clinton continued his "Remember How Awesome I Am" t... http://t.co/wlcpqQSX</text>
	<name>hootchristian</name>
</tweet>
<tweet>
	<text>I'm not all into red carpet fashion, but Michelle Dockery did look stunning tonight at the Golden Globes http://t.co/jNkQcJaB</text>
	<name>egaal</name>
</tweet>
<tweet>
	<text>Catching up with the rest of absolutely everyone; finally watching The Golden Globes. #2013</text>
	<name>AleksLyanskaya</name>
</tweet>
<tweet>
	<text>Jessica Chastain, Best Actress Drama Winner At Golden Globes 2013 http://t.co/osJyTLfw</text>
	<name>LimpaGhosh</name>
</tweet>
<tweet>
	<text>Golden Globes 2013: What the Stars Wore! http://t.co/N0827vhF</text>
	<name>CelebrityNewsCo</name>
</tweet>
<tweet>
	<text>Golden Globes 2013: What the Stars Wore! http://t.co/rPnXAjza</text>
	<name>CelebrityCutes</name>
</tweet>
<tweet>
	<text>'Girls' Night: HBO Series Nabs Two Golden Globes http://t.co/N7TJr0Q1</text>
	<name>Xclusivemii</name>
</tweet>
<tweet>
	<text>Golden Globe Awards 2013 Winners List - Who were the big winners at the 2013 Globes? Read on for the full... http://t.co/66MjW5wu</text>
	<name>anoems</name>
</tweet>
<tweet>
	<text>Jessica Chastain, Best Actress Drama Winner At Golden Globes 2013 http://t.co/ILh9leHi</text>
	<name>DilipSinha3</name>
</tweet>
<tweet>
	<text>RT @THR: Complete list of the winners at the 70th annual #GoldenGlobe awards. http://t.co/s60a0iGo</text>
	<name>galacticasitrep</name>
</tweet>
<tweet>
	<text>Golden Globes 2013 Worst-Dressed List: See The Fashion Flops Of The Night! (PHOTOS) http://t.co/rST3PSpg</text>
	<name>LimpaGhosh</name>
</tweet>
<tweet>
	<text>Golden Globes 2013: What the Stars Wore! http://t.co/Yints0J5</text>
	<name>CelebrityPearls</name>
</tweet>
<tweet>
	<text>Golden Globes 2013: What the Stars Wore! http://t.co/ftbVbgvY</text>
	<name>whatsonyormind</name>
</tweet>
<tweet>
	<text>I imagine the Golden Globes after party at the Beverly Hilton is basically a Hallowhedon party with a black tie dress code.</text>
	<name>FootyGirl88</name>
</tweet>
<tweet>
	<text>http://t.co/XYil11rS Golden Globes 2013: 'Homeland,' 'Girls' and 'Game Change' Dominate TV Wins</text>
	<name>VintageVHS</name>
</tweet>
<tweet>
	<text>Golden Globes 2013: What the Stars Wore! http://t.co/FndpjDNl</text>
	<name>CelebrityKimin</name>
</tweet>
<tweet>
	<text>Jessica Chastain, Best Actress Drama Winner At Golden Globes 2013 http://t.co/dPf1av8Y</text>
	<name>BhaskarBanerje4</name>
</tweet>
<tweet>
	<text>Golden Globes 2013 Worst-Dressed List: See The Fashion Flops Of The Night! (PHOTOS) http://t.co/oYHdGI1V</text>
	<name>DilipSinha3</name>
</tweet>
<tweet>
	<text>RT @LaAbuela961: Hay personas que solo compran ropa en Jacarandas pero se pasaron criticando los vestuarios de los famosos en los Golden Globes. #NoMeJodan</text>
	<name>AlBostero</name>
</tweet>
<tweet>
	<text>Golden Globes 2013 Worst-Dressed List: See The Fashion Flops Of The Night! (PHOTOS) http://t.co/kIayYL8v</text>
	<name>HimadriGupta</name>
</tweet>
<tweet>
	<text>@ladygotika nop lo estoy descargando jeje vi los golden globes</text>
	<name>Agnesar86</name>
</tweet>
<tweet>
	<text>Jodie Foster Officially Comes Out as Gay in Moving Golden Globes Speech http://t.co/5Y6d15Nl</text>
	<name>CelebrityPearls</name>
</tweet>
<tweet>
	<text>Jodie Foster Officially Comes Out as Gay in Moving Golden Globes Speech http://t.co/dtH2qnkz</text>
	<name>whatsonyormind</name>
</tweet>
<tweet>
	<text>RT @LaAbuela961: Hay personas que solo compran ropa en Jacarandas pero se pasaron criticando los vestuarios de los famosos en los Golden Globes. #NoMeJodan</text>
	<name>SoySaladoSV</name>
</tweet>
<tweet>
	<text>Golden Globes 2013: What the Stars Wore! http://t.co/c4ndoegB</text>
	<name>CelebrityCell1</name>
</tweet>
<tweet>
	<text>#Google #Hot #News See Three of the Hottest Hairstyles from the Golden Globes http://t.co/ERTZ3FCq #InstantFollowBack YCNews</text>
	<name>Towanda_Vlloa</name>
</tweet>
<tweet>
	<text>"The golden globes are the Canada of awards shows" - Mad Mike the Bike</text>
	<name>_elkue</name>
</tweet>
<tweet>
	<text>Golden Globes 2013: What the Stars Wore! http://t.co/st8SJYUC</text>
	<name>MagenMagin</name>
</tweet>
<tweet>
	<text>RT @LaAbuela961: Hay personas que solo compran ropa en Jacarandas pero se pasaron criticando los vestuarios de los famosos en los Golden Globes. #NoMeJodan</text>
	<name>GillianBarre</name>
</tweet>
<tweet>
	<text>Lea Michele Shows Off Super-Tan Body at 2013 Golden Globes http://t.co/zDnzBkB5</text>
	<name>CelebrityPearls</name>
</tweet>
<tweet>
	<text>Golden Globes 2013 Worst-Dressed List: See The Fashion Flops Of The Night! (PHOTOS) http://t.co/sEf9nkMJ</text>
	<name>BhaskarBanerje4</name>
</tweet>
<tweet>
	<text>Jodie Foster Officially Comes Out as Gay in Moving Golden Globes Speech http://t.co/D9HS9qpc</text>
	<name>CelebrityCutes</name>
</tweet>
<tweet>
	<text>'Les Miserables' Best Picture, Musical Or Comedy Winner At 2013 Golden Globes http://t.co/2HSb6ApS</text>
	<name>LimpaGhosh</name>
</tweet>
<tweet>
	<text>Golden Globes 2013: What the Stars Wore! http://t.co/UoodWCFC</text>
	<name>CelebrityUsa1</name>
</tweet>
<tweet>
	<text>Lea Michele Shows Off Super-Tan Body at 2013 Golden Globes http://t.co/FxHmkEdj</text>
	<name>whatsonyormind</name>
</tweet>
</root>